edu_to_analytics_web_edu-1.0.3-py3.9-nspkg.pth
edu_to_analytics/data/__init__.py
edu_to_analytics/data/apps.py
edu_to_analytics/data/tasks.py
edu_to_analytics/data/utils.py
edu_to_analytics_web_edu-1.0.3.dist-info/METADATA
edu_to_analytics_web_edu-1.0.3.dist-info/WHEEL
edu_to_analytics_web_edu-1.0.3.dist-info/namespace_packages.txt
edu_to_analytics_web_edu-1.0.3.dist-info/top_level.txt
edu_to_analytics_web_edu-1.0.3.dist-info/RECORD
