Metadata-Version: 2.1
Name: edu-to-analytics-web_edu
Version: 1.0.3
Summary: Реализация провайдера данных для ЭШ, отправляемых через веб-сервис в
Home-page: https://stash.bars-open.ru/projects/EDUBASE/repos/edu_to_analytics
Author: БАРС Груп
Author-email: education_dev@bars-open.ru
Requires-Dist: edu-to-analytics-service <2,>=1.1.0
Requires-Dist: Django <4,>=1.11.20
Requires-Dist: spyne <3,>=2.2.14
Requires-Dist: m3-spyne-smev <2,>=1.0.0
